Metadata-Version: 1.1
Name: secure-password
Version: 1.8
Summary: A very easy password generator
Home-page: UNKNOWN
Author: Invisible Medusa
Author-email: invisiblemedusa10@gmail.com
License: MIT
Keywords: Password Generator
Platform: UNKNOWN
Classifier: Development Status :: 5 - Production/Stable
Classifier: Intended Audience :: Education
Classifier: Operating System :: Microsoft :: Windows :: Windows 10
Classifier: License :: OSI Approved :: MIT License
Classifier: Programming Language :: Python :: 3
